[

  {
    "id": 401,
    "name": "Bravura",
    "category": "Saloons",
    "modifications": "Transfender",
    "modelName": "bravura"
  },
  {
    "id": 402,
    "name": "Buffalo",
    "category": "Sport Vehicles",
    "modifications": "Transfender",
    "modelName": "buffalo"
  },
  {
    "id": 403,
    "name": "Linerunner",
    "category": "Industrial",
    "modifications": "None",
    "modelName": "linerun"
  },
  {
    "id": 404,
    "name": "Perennial",
    "category": "Station Wagons",
    "modifications": "Transfender",
    "modelName": "peren"
  },
  {
    "id": 405,
    "name": "Sentinel",
    "category": "Saloons",
    "modifications": "Transfender",
    "modelName": "sentinel"
  },
  {
    "id": 406,
    "name": "Dumper",
    "category": "Unique Vehicles",
    "modifications": "None",
    "modelName": "dumper"
  },
  {
    "id": 407,
    "name": "Firetruck",
    "category": "Public Service",
    "modifications": "None",
    "modelName": "firetruk"
  },
  {
    "id": 408,
    "name": "Trashmaster",
    "category": "Industrial",
    "modifications": "None",
    "modelName": "trash"
  },
  {
    "id": 409,
    "name": "Stretch",
    "category": "Unique Vehicles",
    "modifications": "Transfender",
    "modelName": "stretch"
  },
  {
    "id": 410,
    "name": "Manana",
    "category": "Saloons",
    "modifications": "Transfender",
    "modelName": "manana"
  },
  {
    "id": 411,
    "name": "Infernus",
    "category": "Sport Vehicles",
    "modifications": "Transfender",
    "modelName": "infernus"
  },
  {
    "id": 412,
    "name": "Voodoo",
    "category": "Lowriders",
    "modifications": "Loco Low Co",
    "modelName": "voodoo"
  },
  {
    "id": 413,
    "name": "Pony",
    "category": "Industrial",
    "modifications": "None",
    "modelName": "pony"
  },
  {
    "id": 414,
    "name": "Mule",
    "category": "Industrial",
    "modifications": "None",
    "modelName": "mule"
  },
  {
    "id": 415,
    "name": "Cheetah",
    "category": "Sport Vehicles",
    "modifications": "Transfender",
    "modelName": "cheetah"
  },
  {
    "id": 416,
    "name": "Ambulance",
    "category": "Public Service",
    "modifications": "None",
    "modelName": "ambulan"
  },
  {
    "id": 417,
    "name": "Leviathan",
    "category": "Helicopters",
    "modifications": "None",
    "modelName": "leviathn"
  },
  {
    "id": 418,
    "name": "Moonbeam",
    "category": "Station Wagons",
    "modifications": "Transfender",
    "modelName": "moonbeam"
  },
  {
    "id": 419,
    "name": "Esperanto",
    "category": "Saloons",
    "modifications": "Transfender",
    "modelName": "esperant"
  },
  {
    "id": 420,
    "name": "Taxi",
    "category": "Public Service",
    "modifications": "Transfender",
    "modelName": "taxi"
  },
  {
    "id": 421,
    "name": "Washington",
    "category": "Saloons",
    "modifications": "Transfender",
    "modelName": "washin"
  },
  {
    "id": 422,
    "name": "Bobcat",
    "category": "Industrial",
    "modifications": "Transfender",
    "modelName": "bobcat"
  },
  {
    "id": 423,
    "name": "Mr Whoopee",
    "category": "Unique Vehicles",
    "modifications": "None",
    "modelName": "mrwhoop"
  },
  {
    "id": 424,
    "name": "BF Injection",
    "category": "Off Road",
    "modifications": "Transfender",
    "modelName": "bfinject"
  },
  {
    "id": 425,
    "name": "Hunter",
    "category": "Helicopters",
    "modifications": "None",
    "modelName": "hunter"
  },
  {
    "id": 426,
    "name": "Premier",
    "category": "Saloons",
    "modifications": "Transfender",
    "modelName": "premier"
  },
  {
    "id": 427,
    "name": "Enforcer",
    "category": "Public Service",
    "modifications": "None",
    "modelName": "enforcer"
  },
  {
    "id": 428,
    "name": "Securicar",
    "category": "Public Service",
    "modifications": "None",
    "modelName": "securica"
  },
  {
    "id": 429,
    "name": "Banshee",
    "category": "Sport Vehicles",
    "modifications": "Transfender",
    "modelName": "banshee"
  },
  {
    "id": 430,
    "name": "Predator",
    "category": "Boats",
    "modifications": "None",
    "modelName": "predator"
  },
  {
    "id": 431,
    "name": "Bus",
    "category": "Public Service",
    "modifications": "Transfender",
    "modelName": "bus"
  },
  {
    "id": 432,
    "name": "Rhino",
    "category": "Public Service",
    "modifications": "None",
    "modelName": "rhino"
  },
  {
    "id": 433,
    "name": "Barracks",
    "category": "Public Service",
    "modifications": "None",
    "modelName": "barracks"
  },
  {
    "id": 434,
    "name": "Hotknife",
    "category": "Unique Vehicles",
    "modifications": "None",
    "modelName": "hotknife"
  },
  {
    "id": 435,
    "name": "Article Trailer",
    "category": "Trailers",
    "modifications": "None",
    "modelName": "artict1"
  },
  {
    "id": 436,
    "name": "Previon",
    "category": "Saloons",
    "modifications": "Transfender",
    "modelName": "previon"
  },
  {
    "id": 437,
    "name": "Coach",
    "category": "Public Service",
    "modifications": "None",
    "modelName": "coach"
  },
  {
    "id": 438,
    "name": "Cabbie",
    "category": "Public Service",
    "modifications": "Transfender",
    "modelName": "cabbie"
  },
  {
    "id": 439,
    "name": "Stallion",
    "category": "Sports",
    "modifications": "Transfender",
    "modelName": "stalion"
  },
  {
    "id": 440,
    "name": "Rumpo",
    "category": "Industrial",
    "modifications": "Transfender",
    "modelName": "rumpo"
  },
  {
    "id": 441,
    "name": "RC Bandit",
    "category": "Remote Control",
    "modifications": "None",
    "modelName": "rcbandit"
  },
  {
    "id": 442,
    "name": "Romero",
    "category": "Public Service",
    "modifications": "None",
    "modelName": "romero"
  },
  {
    "id": 443,
    "name": "Packer",
    "category": "Industrial",
    "modifications": "None",
    "modelName": "packer"
  },
  {
    "id": 444,
    "name": "Monster",
    "category": "Off Road",
    "modifications": "Transfender",
    "modelName": "monster"
  },
  {
    "id": 445,
    "name": "Admiral",
    "category": "Saloons",
    "modifications": "Transfender",
    "modelName": "admiral"
  },
  {
    "id": 446,
    "name": "Squalo",
    "category": "Boats",
    "modifications": "None",
    "modelName": "squalo"
  },
  {
    "id": 447,
    "name": "Seasparrow",
    "category": "Helicopters",
    "modifications": "None",
    "modelName": "seaspar"
  },
  {
    "id": 448,
    "name": "Pizzaboy",
    "category": "Motorcycles",
    "modifications": "Transfender",
    "modelName": "pizzaboy"
  },
  {
    "id": 449,
    "name": "Tram",
    "category": "Public Service",
    "modifications": "None",
    "modelName": "tram"
  },
  {
    "id": 450,
    "name": "Article Trailer 2",
    "category": "Trailers",
    "modifications": "None",
    "modelName": "artict2"
  },
  {
    "id": 451,
    "name": "Turismo",
    "category": "Sport Vehicles",
    "modifications": "Transfender",
    "modelName": "turismo"
  },
  {
    "id": 452,
    "name": "Speeder",
    "category": "Boats",
    "modifications": "None",
    "modelName": "speeder"
  },
  {
    "id": 453,
    "name": "Reefer",
    "category": "Boats",
    "modifications": "None",
    "modelName": "reefer"
  },
  {
    "id": 454,
    "name": "Tropic",
    "category": "Boats",
    "modifications": "None",
    "modelName": "tropic"
  },
  {
    "id": 455,
    "name": "Flatbed",
    "category": "Industrial",
    "modifications": "None",
    "modelName": "flatbed"
  },
  {
    "id": 456,
    "name": "Yankee",
    "category": "Industrial",
    "modifications": "None",
    "modelName": "yankee"
  },
  {
    "id": 457,
    "name": "Caddy",
    "category": "Unique Vehicles",
    "modifications": "None",
    "modelName": "caddy"
  },
  {
    "id": 458,
    "name": "Solair",
    "category": "Saloons",
    "modifications": "Transfender",
    "modelName": "solair"
  },
  {
    "id": 459,
    "name": "Topfun Van",
    "category": "Unique Vehicles",
    "modifications": "None",
    "modelName": "topfun"
  },
  {
    "id": 460,
    "name": "Skimmer",
    "category": "Boats",
    "modifications": "None",
    "modelName": "skimmer"
  },
  {
    "id": 461,
    "name": "PCJ-600",
    "category": "Motorcycles",
    "modifications": "Transfender",
    "modelName": "pcj600"
  },
  {
    "id": 462,
    "name": "Faggio",
    "category": "Motorcycles",
    "modifications": "Transfender",
    "modelName": "faggio"
  },
  {
    "id": 463,
    "name": "Freeway",
    "category": "Motorcycles",
    "modifications": "Transfender",
    "modelName": "freeway"
  },
  {
    "id": 464,
    "name": "RC Baron",
    "category": "Remote Control",
    "modifications": "None",
    "modelName": "rcbaron"
  },
  {
    "id": 465,
    "name": "RC Raider",
    "category": "Remote Control",
    "modifications": "None",
    "modelName": "rcraider"
  },
  {
    "id": 466,
    "name": "Glendale",
    "category": "Saloons",
    "modifications": "Transfender",
    "modelName": "glendale"
  },
  {
    "id": 467,
    "name": "Oceanic",
    "category": "Saloons",
    "modifications": "Transfender",
    "modelName": "oceanic"
  },
  {
    "id": 468,
    "name": "Sanchez",
    "category": "Motorcycles",
    "modifications": "Transfender",
    "modelName": "sanchez"
  },
  {
    "id": 469,
    "name": "Sparrow",
    "category": "Helicopters",
    "modifications": "None",
    "modelName": "sparrow"
  },
  {
    "id": 470,
    "name": "Patriot",
    "category": "Off Road",
    "modifications": "Transfender",
    "modelName": "patriot"
  },
  {
    "id": 471,
    "name": "Quad",
    "category": "Motorcycles",
    "modifications": "None",
    "modelName": "quad"
  },
  {
    "id": 472,
    "name": "Coastguard",
    "category": "Boats",
    "modifications": "None",
    "modelName": "coastg"
  },
  {
    "id": 473,
    "name": "Dinghy",
    "category": "Boats",
    "modifications": "None",
    "modelName": "dinghy"
  },
  {
    "id": 474,
    "name": "Hermes",
    "category": "Lowriders",
    "modifications": "Loco Low Co",
    "modelName": "hermes"
  },
  {
    "id": 475,
    "name": "Sabre",
    "category": "Sports",
    "modifications": "Transfender",
    "modelName": "sabre"
  },
  {
    "id": 476,
    "name": "Rustler",
    "category": "Planes",
    "modifications": "None",
    "modelName": "rustler"
  },
  {
    "id": 477,
    "name": "ZR-350",
    "category": "Sports",
    "modifications": "Transfender",
    "modelName": "zr350"
  },
  {
    "id": 478,
    "name": "Walton",
    "category": "Industrial",
    "modifications": "Transfender",
    "modelName": "walton"
  },
  {
    "id": 479,
    "name": "Regina",
    "category": "Station Wagons",
    "modifications": "Transfender",
    "modelName": "regina"
  },
  {
    "id": 480,
    "name": "Comet",
    "category": "Sport Vehicles",
    "modifications": "Transfender",
    "modelName": "comet"
  },
  {
    "id": 481,
    "name": "BMX",
    "category": "Bicycles",
    "modifications": "None",
    "modelName": "bmx"
  },
  {
    "id": 482,
    "name": "Burrito",
    "category": "Industrial",
    "modifications": "Transfender",
    "modelName": "burrito"
  },
  {
    "id": 483,
    "name": "Camper",
    "category": "Industrial",
    "modifications": "None",
    "modelName": "camper"
  },
  {
    "id": 484,
    "name": "Marquis",
    "category": "Boats",
    "modifications": "None",
    "modelName": "marquis"
  },
  {
    "id": 485,
    "name": "Baggage",
    "category": "Public Service",
    "modifications": "None",
    "modelName": "baggage"
  },
  {
    "id": 486,
    "name": "Dozer",
    "category": "Unique Vehicles",
    "modifications": "None",
    "modelName": "dozer"
  },
  {
    "id": 487,
    "name": "Maverick",
    "category": "Helicopters",
    "modifications": "None",
    "modelName": "maverick"
  },
  {
    "id": 500,
    "name": "Mesa",
    "category": "Off Road",
    "modifications": "Transfender",
    "modelName": "mesa"
  },
  {
    "id": 501,
    "name": "RC Goblin",
    "category": "RC Vehicles",
    "modifications": "None",
    "modelName": "rcgoblin"
  },
  {
    "id": 502,
    "name": "Hotring Racer A",
    "category": "Sport Vehicles",
    "modifications": "None",
    "modelName": "hotrina"
  },
  {
    "id": 488,
    "name": "SAN News Maverick",
    "category": "Helicopters",
    "modifications": "None",
    "modelName": "vcnmav"
  },
  {
    "id": 489,
    "name": "Rancher",
    "category": "Off Road",
    "modifications": "Transfender",
    "modelName": "rancher"
  },
  {
    "id": 490,
    "name": "FBI Rancher",
    "category": "Public Service",
    "modifications": "None",
    "modelName": "fbiranch"
  },
  {
    "id": 491,
    "name": "Virgo",
    "category": "Saloons",
    "modifications": "Transfender",
    "modelName": "virgo"
  },
  {
    "id": 492,
    "name": "Greenwood",
    "category": "Saloons",
    "modifications": "Transfender",
    "modelName": "greenwoo"
  },
  {
    "id": 493,
    "name": "Jetmax",
    "category": "Boats",
    "modifications": "None",
    "modelName": "jetmax"
  },
  {
    "id": 494,
    "name": "Hotring Racer",
    "category": "Sport Vehicles",
    "modifications": "None",
    "modelName": "hotring"
  },
  {
    "id": 495,
    "name": "Sandking",
    "category": "Off Road",
    "modifications": "None",
    "modelName": "sandking"
  },
  {
    "id": 496,
    "name": "Blista Compact",
    "category": "Sport Vehicles",
    "modifications": "Transfender",
    "modelName": "blistac"
  },
  {
    "id": 497,
    "name": "Police Maverick",
    "category": "Helicopters",
    "modifications": "None",
    "modelName": "polmav"
  },
  {
    "id": 498,
    "name": "Boxville",
    "category": "Industrial",
    "modifications": "None",
    "modelName": "boxville"
  },
  {
    "id": 499,
    "name": "Benson",
    "category": "Industrial",
    "modifications": "None",
    "modelName": "benson"
  },
  {
    "id": 500,
    "name": "Mesa",
    "category": "Off Road",
    "modifications": "Transfender",
    "modelName": "mesa"
  },
  {
    "id": 503,
    "name": "Hotring Racer B",
    "category": "Sport Vehicles",
    "modifications": "None",
    "modelName": "hotrinb"
  },
  {
    "id": 504,
    "name": "Bloodring Banger",
    "category": "Saloons",
    "modifications": "None",
    "modelName": "bloodra / bloodrb"
  },
  {
    "id": 505,
    "name": "Rancher Lure",
    "category": "Off Road",
    "modifications": "None",
    "modelName": "rnchlure"
  },
  {
    "id": 506,
    "name": "Super GT",
    "category": "Sport Vehicles",
    "modifications": "Transfender",
    "modelName": "supergt"
  },
  {
    "id": 507,
    "name": "Elegant",
    "category": "Saloons",
    "modifications": "Transfender",
    "modelName": "elegant"
  },
  {
    "id": 508,
    "name": "Journey",
    "category": "Unique Vehicles",
    "modifications": "None",
    "modelName": "journey"
  },
  {
    "id": 509,
    "name": "Bike",
    "category": "Bikes",
    "modifications": "None",
    "modelName": "bike"
  },
  {
    "id": 510,
    "name": "Mountain Bike",
    "category": "Bikes",
    "modifications": "None",
    "modelName": "mtbike"
  },
  {
    "id": 511,
    "name": "Beagle",
    "category": "Airplane",
    "modifications": "None",
    "modelName": "beagle"
  },
  {
    "id": 512,
    "name": "Cropduster",
    "category": "Airplane",
    "modifications": "None",
    "modelName": "cropdust"
  },
  {
    "id": 513,
    "name": "Stuntplane",
    "category": "Airplane",
    "modifications": "None",
    "modelName": "stunt"
  },
  {
    "id": 514,
    "name": "Tanker",
    "category": "Industrial",
    "modifications": "None",
    "modelName": "petro"
  },
  {
    "id": 515,
    "name": "Roadtrain",
    "category": "Industrial",
    "modifications": "None",
    "modelName": "rdtrain"
  },
  {
    "id": 516,
    "name": "Nebula",
    "category": "Saloons",
    "modifications": "Transfender",
    "modelName": "nebula"
  },
  {
    "id": 517,
    "name": "Majestic",
    "category": "Saloons",
    "modifications": "Transfender",
    "modelName": "majestic"
  },
  {
    "id": 518,
    "name": "Buccaneer",
    "category": "Saloons",
    "modifications": "Transfender",
    "modelName": "buccanee"
  },
  {
    "id": 519,
    "name": "Shamal",
    "category": "Airplane",
    "modifications": "None",
    "modelName": "shamal"
  },
  {
    "id": 520,
    "name": "Hydra",
    "category": "Airplane",
    "modifications": "None",
    "modelName": "hydra"
  },
  {
    "id": 521,
    "name": "FCR-900",
    "category": "Bikes",
    "modifications": "None",
    "modelName": "fcr900"
  },
  {
    "id": 522,
    "name": "NRG-500",
    "category": "Bikes",
    "modifications": "None",
    "modelName": "nrg500"
  },
  {
    "id": 523,
    "name": "HPV1000",
    "category": "Public Service",
    "modifications": "None",
    "modelName": "copbike"
  },
  {
    "id": 524,
    "name": "Cement Truck",
    "category": "Industrial",
    "modifications": "None",
    "modelName": "cement"
  },
  {
    "id": 525,
    "name": "Towtruck",
    "category": "Unique Vehicles",
    "modifications": "None",
    "modelName": "towtruck"
  },
  {
    "id": 526,
    "name": "Fortune",
    "category": "Saloons",
    "modifications": "Transfender",
    "modelName": "fortune"
  },
  {
    "id": 527,
    "name": "Cadrona",
    "category": "Saloons",
    "modifications": "Transfender",
    "modelName": "cadrona"
  },
  {
    "id": 528,
    "name": "FBI Truck",
    "category": "Public Service",
    "modifications": "None",
    "modelName": "fbitruck"
  },
  {
    "id": 529,
    "name": "Willard",
    "category": "Saloons",
    "modifications": "Transfender",
    "modelName": "willard"
  },
  {
    "id": 530,
    "name": "Forklift",
    "category": "Unique Vehicles",
    "modifications": "None",
    "modelName": "forklift"
  },
  {
    "id": 530,
    "name": "Forklift",
    "category": "Unique Vehicles",
    "modifications": "None",
    "modelName": "forklift"
  },
  {
    "id": 531,
    "name": "Tractor",
    "category": "Industrial",
    "modifications": "None",
    "modelName": "tractor"
  },
  {
    "id": 532,
    "name": "Combine Harvester",
    "category": "Unique Vehicles",
    "modifications": "None",
    "modelName": "combine"
  },
  {
    "id": 533,
    "name": "Feltzer",
    "category": "Convertibles",
    "modifications": "Transfender",
    "modelName": "feltzer"
  },
  {
    "id": 534,
    "name": "Remington",
    "category": "Lowriders",
    "modifications": "Loco Low Co",
    "modelName": "remingtn"
  },
  {
    "id": 535,
    "name": "Slamvan",
    "category": "Lowriders",
    "modifications": "Loco Low Co",
    "modelName": "slamvan"
  },
  {
    "id": 536,
    "name": "Blade",
    "category": "Lowriders",
    "modifications": "Loco Low Co",
    "modelName": "blade"
  },
  {
    "id": 537,
    "name": "Freight (Train)",
    "category": "Unique Vehicles",
    "modifications": "None",
    "modelName": "freight"
  },
  {
    "id": 538,
    "name": "Brownstreak (Train)",
    "category": "Unique Vehicles",
    "modifications": "None",
    "modelName": "streak"
  },
  {
    "id": 539,
    "name": "Vortex",
    "category": "Unique Vehicles",
    "modifications": "None",
    "modelName": "vortex"
  },
  {
    "id": 540,
    "name": "Vincent",
    "category": "Saloons",
    "modifications": "Transfender",
    "modelName": "vincent"
  },
  {
    "id": 541,
    "name": "Bullet",
    "category": "Sport Vehicles",
    "modifications": "Transfender",
    "modelName": "bullet"
  },
  {
    "id": 542,
    "name": "Clover",
    "category": "Saloons",
    "modifications": "Transfender",
    "modelName": "clover"
  },
  {
    "id": 543,
    "name": "Sadler",
    "category": "Industrial",
    "modifications": "None",
    "modelName": "sadler"
  },
  {
    "id": 544,
    "name": "Firetruck LA",
    "category": "Public Service",
    "modifications": "None",
    "modelName": "firela"
  },
  {
    "id": 545,
    "name": "Hustler",
    "category": "Unique Vehicles",
    "modifications": "Transfender",
    "modelName": "hustler"
  },
  {
    "id": 546,
    "name": "Intruder",
    "category": "Saloons",
    "modifications": "Transfender",
    "modelName": "intruder"
  },
  {
    "id": 547,
    "name": "Primo",
    "category": "Saloons",
    "modifications": "Transfender",
    "modelName": "primo"
  },
  {
    "id": 548,
    "name": "Cargobob",
    "category": "Helicopters",
    "modifications": "None",
    "modelName": "cargobob"
  },
  {
    "id": 549,
    "name": "Tampa",
    "category": "Saloons",
    "modifications": "Transfender",
    "modelName": "tampa"
  },
  {
    "id": 550,
    "name": "Sunrise",
    "category": "Saloons",
    "modifications": "Transfender",
    "modelName": "sunrise"
  },
  {
    "id": 551,
    "name": "Merit",
    "category": "Saloons",
    "modifications": "Transfender",
    "modelName": "merit"
  },
  {
    "id": 552,
    "name": "Utility Van",
    "category": "Industrial",
    "modifications": "None",
    "modelName": "utility"
  },
  {
    "id": 553,
    "name": "Nevada",
    "category": "Airplane",
    "modifications": "None",
    "modelName": "nevada"
  },
  {
    "id": 554,
    "name": "Yosemite",
    "category": "Industrial",
    "modifications": "None",
    "modelName": "yosemite"
  },
  {
    "id": 555,
    "name": "Windsor",
    "category": "Convertibles",
    "modifications": "Transfender",
    "modelName": "windsor"
  },
  {
    "id": 556,
    "name": "Monster \"A\"",
    "category": "Off Road",
    "modifications": "None",
    "modelName": "monstera"
  },
  {
    "id": 557,
    "name": "Monster \"B\"",
    "category": "Off Road",
    "modifications": "None",
    "modelName": "monsterb"
  },
  {
    "id": 558,
    "name": "Uranus",
    "category": "Sport Vehicles",
    "modifications": "Wheel Arch Angels",
    "modelName": "uranus"
  },
  {
    "id": 559,
    "name": "Jester",
    "category": "Sport Vehicles",
    "modifications": "Wheel Arch Angels",
    "modelName": "jester"
  },  {
    "id": 530,
    "name": "Forklift",
    "category": "Unique Vehicles",
    "modifications": "None",
    "modelName": "forklift"
  },
  {
    "id": 531,
    "name": "Tractor",
    "category": "Industrial",
    "modifications": "None",
    "modelName": "tractor"
  },
  {
    "id": 532,
    "name": "Combine Harvester",
    "category": "Unique Vehicles",
    "modifications": "None",
    "modelName": "combine"
  },
  {
    "id": 533,
    "name": "Feltzer",
    "category": "Convertibles",
    "modifications": "Transfender",
    "modelName": "feltzer"
  },
  {
    "id": 534,
    "name": "Remington",
    "category": "Lowriders",
    "modifications": "Loco Low Co",
    "modelName": "remingtn"
  },
  {
    "id": 535,
    "name": "Slamvan",
    "category": "Lowriders",
    "modifications": "Loco Low Co",
    "modelName": "slamvan"
  },
  {
    "id": 536,
    "name": "Blade",
    "category": "Lowriders",
    "modifications": "Loco Low Co",
    "modelName": "blade"
  },
  {
    "id": 537,
    "name": "Freight (Train)",
    "category": "Unique Vehicles",
    "modifications": "None",
    "modelName": "freight"
  },
  {
    "id": 538,
    "name": "Brownstreak (Train)",
    "category": "Unique Vehicles",
    "modifications": "None",
    "modelName": "streak"
  },
  {
    "id": 539,
    "name": "Vortex",
    "category": "Unique Vehicles",
    "modifications": "None",
    "modelName": "vortex"
  },
  {
    "id": 540,
    "name": "Vincent",
    "category": "Saloons",
    "modifications": "Transfender",
    "modelName": "vincent"
  },
  {
    "id": 541,
    "name": "Bullet",
    "category": "Sport Vehicles",
    "modifications": "Transfender",
    "modelName": "bullet"
  },
  {
    "id": 542,
    "name": "Clover",
    "category": "Saloons",
    "modifications": "Transfender",
    "modelName": "clover"
  },
  {
    "id": 543,
    "name": "Sadler",
    "category": "Industrial",
    "modifications": "None",
    "modelName": "sadler"
  },
  {
    "id": 544,
    "name": "Firetruck LA",
    "category": "Public Service",
    "modifications": "None",
    "modelName": "firela"
  },
  {
    "id": 545,
    "name": "Hustler",
    "category": "Unique Vehicles",
    "modifications": "Transfender",
    "modelName": "hustler"
  },
  {
    "id": 546,
    "name": "Intruder",
    "category": "Saloons",
    "modifications": "Transfender",
    "modelName": "intruder"
  },
  {
    "id": 547,
    "name": "Primo",
    "category": "Saloons",
    "modifications": "Transfender",
    "modelName": "primo"
  },
  {
    "id": 548,
    "name": "Cargobob",
    "category": "Helicopters",
    "modifications": "None",
    "modelName": "cargobob"
  },
  {
    "id": 549,
    "name": "Tampa",
    "category": "Saloons",
    "modifications": "Transfender",
    "modelName": "tampa"
  },
  {
    "id": 550,
    "name": "Sunrise",
    "category": "Saloons",
    "modifications": "Transfender",
    "modelName": "sunrise"
  },
  {
    "id": 551,
    "name": "Merit",
    "category": "Saloons",
    "modifications": "Transfender",
    "modelName": "merit"
  },
  {
    "id": 552,
    "name": "Utility Van",
    "category": "Industrial",
    "modifications": "None",
    "modelName": "utility"
  },
  {
    "id": 553,
    "name": "Nevada",
    "category": "Airplane",
    "modifications": "None",
    "modelName": "nevada"
  },
  {
    "id": 554,
    "name": "Yosemite",
    "category": "Industrial",
    "modifications": "None",
    "modelName": "yosemite"
  },
  {
    "id": 555,
    "name": "Windsor",
    "category": "Convertibles",
    "modifications": "Transfender",
    "modelName": "windsor"
  },
  {
    "id": 556,
    "name": "Monster \"A\"",
    "category": "Off Road",
    "modifications": "None",
    "modelName": "monstera"
  },
  {
    "id": 557,
    "name": "Monster \"B\"",
    "category": "Off Road",
    "modifications": "None",
    "modelName": "monsterb"
  },
  {
    "id": 558,
    "name": "Uranus",
    "category": "Sport Vehicles",
    "modifications": "Wheel Arch Angels",
    "modelName": "uranus"
  },
  {
    "id": 559,
    "name": "Jester",
    "category": "Sport Vehicles",
    "modifications": "Wheel Arch Angels",
    "modelName": "jester"
  },  {
    "id": 560,
    "name": "Sultan",
    "category": "Saloons",
    "modifications": "Wheel Arch Angels",
    "modelName": "sultan"
  },
  {
    "id": 561,
    "name": "Stratum",
    "category": "Station Wagons",
    "modifications": "Wheel Arch Angels",
    "modelName": "stratum"
  },
  {
    "id": 562,
    "name": "Elegy",
    "category": "Saloons",
    "modifications": "Wheel Arch Angels",
    "modelName": "elegy"
  },
  {
    "id": 563,
    "name": "Raindance",
    "category": "Helicopters",
    "modifications": "None",
    "modelName": "raindanc"
  },
  {
    "id": 564,
    "name": "RC Tiger",
    "category": "RC Vehicles",
    "modifications": "None",
    "modelName": "rctiger"
  },
  {
    "id": 565,
    "name": "Flash",
    "category": "Sport Vehicles",
    "modifications": "Wheel Arch Angels",
    "modelName": "flash"
  },
  {
    "id": 566,
    "name": "Tahoma",
    "category": "Lowriders",
    "modifications": "Loco Low Co",
    "modelName": "tahoma"
  },
  {
    "id": 567,
    "name": "Savanna",
    "category": "Lowriders",
    "modifications": "Loco Low Co",
    "modelName": "savanna"
  },
  {
    "id": 568,
    "name": "Bandito",
    "category": "Off Road",
    "modifications": "None",
    "modelName": "bandito"
  },
  {
    "id": 569,
    "name": "Freight Flat Trailer (Train)",
    "category": "Trailers",
    "modifications": "None",
    "modelName": "freiflat"
  },
  {
    "id": 570,
    "name": "Streak Trailer (Train)",
    "category": "Trailers",
    "modifications": "None",
    "modelName": "streakc"
  },
  {
    "id": 571,
    "name": "Kart",
    "category": "Unique Vehicles",
    "modifications": "None",
    "modelName": "kart"
  },
  {
    "id": 572,
    "name": "Mower",
    "category": "Unique Vehicles",
    "modifications": "None",
    "modelName": "mower"
  },
  {
    "id": 573,
    "name": "Dune",
    "category": "Off Road",
    "modifications": "None",
    "modelName": "duneride"
  },
  {
    "id": 574,
    "name": "Sweeper",
    "category": "Unique Vehicles",
    "modifications": "None",
    "modelName": "sweeper"
  },
  {
    "id": 575,
    "name": "Broadway",
    "category": "Lowriders",
    "modifications": "Loco Low Co",
    "modelName": "broadway"
  },
  {
    "id": 576,
    "name": "Tornado",
    "category": "Lowriders",
    "modifications": "Loco Low Co",
    "modelName": "tornado"
  },
  {
    "id": 577,
    "name": "AT400",
    "category": "Airplane",
    "modifications": "None",
    "modelName": "at400"
  },
  {
    "id": 578,
    "name": "DFT-30",
    "category": "Industrial",
    "modifications": "None",
    "modelName": "dft30"
  },
  {
    "id": 579,
    "name": "Huntley",
    "category": "Off Road",
    "modifications": "Transfender",
    "modelName": "huntley"
  },
  {
    "id": 580,
    "name": "Stafford",
    "category": "Saloons",
    "modifications": "Transfender",
    "modelName": "stafford"
  },
  {
    "id": 581,
    "name": "BF-400",
    "category": "Bikes",
    "modifications": "None",
    "modelName": "bf400"
  },
  {
    "id": 582,
    "name": "Newsvan",
    "category": "Industrial",
    "modifications": "None",
    "modelName": "newsvan"
  },
  {
    "id": 583,
    "name": "Tug",
    "category": "Unique Vehicles",
    "modifications": "None",
    "modelName": "tug"
  },
  {
    "id": 584,
    "name": "Petrol Trailer",
    "category": "Trailers",
    "modifications": "None",
    "modelName": "petrotr"
  },
  {
    "id": 585,
    "name": "Emperor",
    "category": "Saloons",
    "modifications": "Transfender",
    "modelName": "emperor"
  },
  {
    "id": 586,
    "name": "Wayfarer",
    "category": "Bikes",
    "modifications": "None",
    "modelName": "wayfarer"
  },
  {
    "id": 587,
    "name": "Euros",
    "category": "Sport Vehicles",
    "modifications": "Transfender",
    "modelName": "euros"
  },
  {
    "id": 588,
    "name": "Hotdog",
    "category": "Unique Vehicles",
    "modifications": "None",
    "modelName": "hotdog"
  },
  {
    "id": 589,
    "name": "Club",
    "category": "Sport Vehicles",
    "modifications": "Transfender",
    "modelName": "club"
  },  {
    "id": 590,
    "name": "Freight Box Trailer (Train)",
    "category": "Trailers",
    "modifications": "None",
    "modelName": "freibox"
  },
  {
    "id": 591,
    "name": "Article Trailer 3",
    "category": "Trailers",
    "modifications": "None",
    "modelName": "artict3"
  },
  {
    "id": 592,
    "name": "Andromada",
    "category": "Airplane",
    "modifications": "None",
    "modelName": "androm"
  },
  {
    "id": 593,
    "name": "Dodo",
    "category": "Airplane",
    "modifications": "None",
    "modelName": "dodo"
  },
  {
    "id": 594,
    "name": "RC Cam",
    "category": "RC Vehicles",
    "modifications": "None",
    "modelName": "rccam"
  },
  {
    "id": 595,
    "name": "Launch",
    "category": "Boats",
    "modifications": "None",
    "modelName": "launch"
  },
  {
    "id": 596,
    "name": "Police Car (LSPD)",
    "category": "Public Service",
    "modifications": "None",
    "modelName": "copcarla"
  },
  {
    "id": 597,
    "name": "Police Car (SFPD)",
    "category": "Public Service",
    "modifications": "None",
    "modelName": "copcarsf"
  },
  {
    "id": 598,
    "name": "Police Car (LVPD)",
    "category": "Public Service",
    "modifications": "None",
    "modelName": "copcarvg"
  },
  {
    "id": 599,
    "name": "Police Ranger",
    "category": "Public Service",
    "modifications": "None",
    "modelName": "copcarru"
  },
  {
    "id": 600,
    "name": "Picador",
    "category": "Industrial",
    "modifications": "Transfender",
    "modelName": "picador"
  },
  {
    "id": 601,
    "name": "S.W.A.T.",
    "category": "Public Service",
    "modifications": "None",
    "modelName": "swatvan"
  },
  {
    "id": 602,
    "name": "Alpha",
    "category": "Sport Vehicles",
    "modifications": "Transfender",
    "modelName": "alpha"
  },
  {
    "id": 603,
    "name": "Phoenix",
    "category": "Sport Vehicles",
    "modifications": "Transfender",
    "modelName": "phoenix"
  },
  {
    "id": 604,
    "name": "Glendale Shit",
    "category": "Saloons",
    "modifications": "None",
    "modelName": "glenshit"
  },
  {
    "id": 605,
    "name": "Sadler Shit",
    "category": "Industrial",
    "modifications": "None",
    "modelName": "sadlshit"
  },
  {
    "id": 606,
    "name": "Baggage Trailer \"A\"",
    "category": "Trailers",
    "modifications": "None",
    "modelName": "bagboxa"
  },
  {
    "id": 607,
    "name": "Baggage Trailer \"B\"",
    "category": "Trailers",
    "modifications": "None",
    "modelName": "bagboxb"
  },
  {
    "id": 608,
    "name": "Tug Stairs Trailer",
    "category": "Trailers",
    "modifications": "None",
    "modelName": "tugstair"
  },
  {
    "id": 609,
    "name": "Boxville",
    "category": "Industrial",
    "modifications": "None",
    "modelName": "boxburg"
  },
  {
    "id": 610,
    "name": "Farm Trailer",
    "category": "Trailers",
    "modifications": "None",
    "modelName": "farmtr1"
  },
  {
    "id": 611,
    "name": "Utility Trailer",
    "category": "Trailers",
    "modifications": "None",
    "modelName": "utiltr1"
  }
]